Metadata-Version: 2.4
Name: rheojax
Version: 0.2.2
Summary: Unified rheological analysis framework with JAX acceleration
Author-email: Wei Chen <wchen@anl.gov>
Maintainer-email: Wei Chen <wchen@anl.gov>
License: MIT License
Project-URL: Homepage, https://github.com/imewei/rheojax
Project-URL: Bug Tracker, https://github.com/imewei/rheojax/issues
Project-URL: Documentation, https://rheojax.readthedocs.io
Project-URL: Source Code, https://github.com/imewei/rheojax
Classifier: Development Status :: 4 - Beta
Classifier: Intended Audience :: Science/Research
Classifier: Topic :: Scientific/Engineering :: Physics
Classifier: License :: OSI Approved :: MIT License
Classifier: Programming Language :: Python :: 3
Classifier: Programming Language :: Python :: 3.12
Classifier: Programming Language :: Python :: 3.13
Classifier: Operating System :: OS Independent
Requires-Python: >=3.12
License-File: LICENSE
Requires-Dist: numpy<3.0.0,>=2.0.0
Requires-Dist: scipy<2.0.0,>=1.16.0
Requires-Dist: pandas<3.0.0,>=2.0.0
Requires-Dist: matplotlib<4.0.0,>=3.10.0
Requires-Dist: nlsq>=0.2.1
Requires-Dist: jax==0.8.0
Requires-Dist: jaxlib==0.8.0
Requires-Dist: numpyro<1.0.0,>=0.19.0
Requires-Dist: arviz<1.0.0,>=0.22.0
Provides-Extra: core
Requires-Dist: piblin-jax>=0.0.3; extra == "core"
Provides-Extra: dev
Requires-Dist: pytest>=9.0.0; extra == "dev"
Requires-Dist: pytest-cov>=7.0.0; extra == "dev"
Requires-Dist: pytest-xdist>=3.8.0; extra == "dev"
Requires-Dist: hypothesis>=6.145.0; extra == "dev"
Requires-Dist: black>=25.11.0; extra == "dev"
Requires-Dist: ruff>=0.14.5; extra == "dev"
Requires-Dist: mypy>=1.18.2; extra == "dev"
Requires-Dist: pre-commit>=4.3.0; extra == "dev"
Requires-Dist: ipython>=9.6.0; extra == "dev"
Requires-Dist: jupyter>=1.1.0; extra == "dev"
Requires-Dist: sphinx>=8.2.0; extra == "dev"
Requires-Dist: sphinx-rtd-theme>=3.0.0; extra == "dev"
Requires-Dist: sphinx-autodoc-typehints>=3.5.0; extra == "dev"
Provides-Extra: ml
Requires-Dist: scikit-learn>=1.7.0; extra == "ml"
Provides-Extra: io
Requires-Dist: h5py>=3.15.0; extra == "io"
Requires-Dist: openpyxl>=3.1.0; extra == "io"
Requires-Dist: xlrd>=2.0.0; extra == "io"
Provides-Extra: all
Requires-Dist: rheojax[core,dev,io,ml]; extra == "all"
Dynamic: license-file
